ltr559/__init__.py
ltr559-0.1.1.dist-info/LICENSE.txt
ltr559-0.1.1.dist-info/METADATA
ltr559-0.1.1.dist-info/WHEEL
ltr559-0.1.1.dist-info/top_level.txt
ltr559-0.1.1.dist-info/RECORD
